LbSoftConfDb2Clients/AppImporter.py
LbSoftConfDb2Clients/GenericClient.py
LbSoftConfDb2Clients/LbSdbAddPlatform.py
LbSoftConfDb2Clients/LbSdbAddProject.py
LbSoftConfDb2Clients/LbSdbBuildTool.py
LbSoftConfDb2Clients/LbSdbDeleteVersion.py
LbSoftConfDb2Clients/LbSdbDumpProjects.py
LbSoftConfDb2Clients/LbSdbGenerateVersionJSON.py
LbSoftConfDb2Clients/LbSdbImport.py
LbSoftConfDb2Clients/LbSdbQuery.py
LbSoftConfDb2Clients/LbSdbRelease.py
LbSoftConfDb2Clients/LbSdbSetPVProperties.py
LbSoftConfDb2Clients/LbSdbSetProjectProperties.py
LbSoftConfDb2Clients/SoftConfDB.py
LbSoftConfDb2Clients/__init__.py
LbSoftConfDb2Clients-2.0.0.dist-info/LICENSE
LbSoftConfDb2Clients-2.0.0.dist-info/METADATA
LbSoftConfDb2Clients-2.0.0.dist-info/WHEEL
LbSoftConfDb2Clients-2.0.0.dist-info/entry_points.txt
LbSoftConfDb2Clients-2.0.0.dist-info/top_level.txt
LbSoftConfDb2Clients-2.0.0.dist-info/zip-safe
LbSoftConfDb2Clients-2.0.0.dist-info/RECORD
