Metadata-Version: 2.1
Name: LbSoftConfDb2Clients
Version: 2.0.0
Summary: LHCb Software configuration database 2 clients
Home-page: https://gitlab.cern.ch/lhcb-core/LbSoftConfDb2Clients
Author: CERN - LHCb Core Software
Author-email: lhcb-core-soft@cern.ch
License: GPLv3+
Platform: UNKNOWN
Classifier: Development Status :: 4 - Beta
Classifier: Intended Audience :: Developers
Classifier: Topic :: Software Development :: Build Tools
Classifier: License :: OSI Approved :: GNU General Public License v3 or later (GPLv3+)
Classifier: Programming Language :: Python :: 2
Classifier: Programming Language :: Python :: 2.7
Classifier: Programming Language :: Python :: 3
Classifier: Programming Language :: Python :: 3.5
Classifier: Programming Language :: Python :: 3.6
Requires-Python: >=2.7
Requires-Dist: LbCommon
Requires-Dist: LbEnv
Requires-Dist: six
